ntps/__init__.py
ntps/client.py
ntps/correction.py
ntps/leap_seconds.py
ntps/packet.py
ntps/py.typed
ntps/refid.py
ntps/server.py
ntps/struct.py
ntps/system.py
ntps-0.5.0.dist-info/METADATA
ntps-0.5.0.dist-info/WHEEL
ntps-0.5.0.dist-info/licenses/LICENSE
ntps-0.5.0.dist-info/RECORD
