Metadata-Version: 2.4
Name: ntps
Version: 0.5.0
Summary: Modern, type-safe, zero-dependency python library for implementing a network time protocol (NTP) stratum 0 server
Project-URL: Source, https://github.com/michealroberts/ntps
Project-URL: Issues, https://github.com/michealroberts/ntps/issues
Project-URL: PullRequests, https://github.com/michealroberts/ntps/pulls
Project-URL: Discussions, https://github.com/michealroberts/ntps/discussions
Author-email: michealroberts <michael@observerly.com>
Maintainer-email: Michael Roberts <michael@observerly.com>
License: MIT License
License-File: LICENSE
Keywords: gnss,gps,network time protocol,network time protocol server,ntp,ntp client,ntp server,stratum-0
Classifier: Development Status :: 3 - Alpha
Classifier: Intended Audience :: Developers
Classifier: License :: OSI Approved :: MIT License
Classifier: Programming Language :: Python :: 3.13
Requires-Python: >=3.13
